primal_grakn/__init__.py
primal_grakn/primal_grakn.py
primal_grakn/test.py
primal_grakn-0.0.1.dist-info/LICENSE
primal_grakn-0.0.1.dist-info/METADATA
primal_grakn-0.0.1.dist-info/WHEEL
primal_grakn-0.0.1.dist-info/top_level.txt
primal_grakn-0.0.1.dist-info/RECORD
