Metadata-Version: 2.1
Name: primal-grakn
Version: 0.0.1
Summary: A convenience wrapper around the official grakn-python client
Home-page: https://github.com/cyclecycle/primal-grakn
Author: Nick Morley
Author-email: nick.morley111@gmail.com
License: UNKNOWN
Platform: UNKNOWN
Classifier: Programming Language :: Python :: 3
Classifier: License :: OSI Approved :: MIT License
Classifier: Operating System :: OS Independent
Requires-Dist: grakn (==1.4.2)
